libmedaka.abi3.so
medaka/__init__.py
medaka/align.py
medaka/common.py
medaka/datastore.py
medaka/executor.py
medaka/features.py
medaka/labels.py
medaka/medaka.py
medaka/medaka_counts.py
medaka/models.py
medaka/options.py
medaka/prediction.py
medaka/rle.py
medaka/smolecule.py
medaka/stitch.py
medaka/torch_ext.py
medaka/training.py
medaka/variant.py
medaka/vcf.py
medaka/architectures/__init__.py
medaka/architectures/base_classes.py
medaka/architectures/gru.py
medaka/architectures/latent_space_lstm.py
medaka/architectures/majority_vote_model.py
medaka/architectures/read_level_modules.py
medaka/data/r1041_e82_400bps_hac_v5.2.0_model_pt.tar.gz
medaka/data/r1041_e82_400bps_hac_variant_v5.0.0_model_pt.tar.gz
medaka/data/r1041_e82_400bps_sup_v5.2.0_model_pt.tar.gz
medaka/data/r1041_e82_400bps_sup_variant_v5.0.0_model_pt.tar.gz
medaka/tandem/__init__.py
medaka/tandem/alignment.py
medaka/tandem/consensus_generator.py
medaka/tandem/io.py
medaka/tandem/polisher.py
medaka/tandem/record_name.py
medaka/tandem/spanning_read_clusterer.py
medaka/tandem/tandem.py
medaka_cpu-2.2.0.data/scripts/medaka_consensus
medaka_cpu-2.2.0.data/scripts/medaka_consensus_joint
medaka_cpu-2.2.0.data/scripts/medaka_variant
medaka_cpu-2.2.0.data/scripts/mini_align
medaka_cpu.libs/libbrotlicommon-6ce2a53c.so.1.0.6
medaka_cpu.libs/libbrotlidec-811d1be3.so.1.0.6
medaka_cpu.libs/libbz2-a1e77c99.so.1.0.6
medaka_cpu.libs/libcom_err-730ca923.so.2.1
medaka_cpu.libs/libcrypt-52aca757.so.1.1.0
medaka_cpu.libs/libcrypto-bdaed0ea.so.1.1.1k
medaka_cpu.libs/libcurl-eaa3cf66.so.4.5.0
medaka_cpu.libs/libdeflate-da676f6e.so.0
medaka_cpu.libs/libgssapi_krb5-323bbd21.so.2.2
medaka_cpu.libs/libidn2-2f4a5893.so.0.3.6
medaka_cpu.libs/libk5crypto-9a74ff38.so.3.1
medaka_cpu.libs/libkeyutils-2777d33d.so.1.6
medaka_cpu.libs/libkrb5-a55300e8.so.3.3
medaka_cpu.libs/libkrb5support-e6594cfc.so.0.1
medaka_cpu.libs/liblber-2-d20824ef.4.so.2.10.9
medaka_cpu-2.2.0.dist-info/METADATA
medaka_cpu-2.2.0.dist-info/WHEEL
medaka_cpu-2.2.0.dist-info/entry_points.txt
medaka_cpu-2.2.0.dist-info/top_level.txt
medaka_cpu-2.2.0.dist-info/RECORD
medaka_cpu-2.2.0.dist-info/licenses/LICENSE
medaka_cpu-2.2.0.dist-info/sboms/auditwheel.cdx.json
